{
  "version": "7",
  "dialect": "postgresql",
  "entries": [
    {
      "idx": 0,
      "version": "7",
      "when": 1777144876135,
      "tag": "0000_blushing_mister_fear",
      "breakpoints": true
    },
    {
      "idx": 1,
      "version": "7",
      "when": 1777150406443,
      "tag": "0001_loving_wasp",
      "breakpoints": true
    },
    {
      "idx": 2,
      "version": "7",
      "when": 1777152223335,
      "tag": "0002_brave_sway",
      "breakpoints": true
    },
    {
      "idx": 3,
      "version": "7",
      "when": 1777168299080,
      "tag": "0003_young_firestar",
      "breakpoints": true
    },
    {
      "idx": 4,
      "version": "7",
      "when": 1777204378087,
      "tag": "0004_smiling_crusher_hogan",
      "breakpoints": true
    },
    {
      "idx": 5,
      "version": "7",
      "when": 1777208224869,
      "tag": "0005_giant_luckman",
      "breakpoints": true
    },
    {
      "idx": 6,
      "version": "7",
      "when": 1777236808377,
      "tag": "0006_typical_mikhail_rasputin",
      "breakpoints": true
    },
    {
      "idx": 7,
      "version": "7",
      "when": 1777276735093,
      "tag": "0007_amazing_deathbird",
      "breakpoints": true
    },
    {
      "idx": 8,
      "version": "7",
      "when": 1777277908493,
      "tag": "0008_classy_violations",
      "breakpoints": true
    },
    {
      "idx": 9,
      "version": "7",
      "when": 1777278060269,
      "tag": "0009_lazy_gunslinger",
      "breakpoints": true
    },
    {
      "idx": 10,
      "version": "7",
      "when": 1777400000000,
      "tag": "0010_skill_fk_drop",
      "breakpoints": true
    },
    {
      "idx": 11,
      "version": "7",
      "when": 1777401000000,
      "tag": "0011_drop_wrong_turn_tables",
      "breakpoints": true
    },
    {
      "idx": 12,
      "version": "7",
      "when": 1777324166393,
      "tag": "0012_right_mentallo",
      "breakpoints": true
    },
    {
      "idx": 13,
      "version": "7",
      "when": 1777776993605,
      "tag": "0013_grey_valeria_richards",
      "breakpoints": true
    }
  ]
}